polyp/__init__.py
polyp/__main__.py
polyp/calltree.py
polyp/fonts.py
polyp/geometry.py
polyp/plotting.py
polyp/plsscript.py
polyp/utils.py
polyp-1.1.5.dist-info/LICENSE.txt
polyp-1.1.5.dist-info/METADATA
polyp-1.1.5.dist-info/WHEEL
polyp-1.1.5.dist-info/entry_points.txt
polyp-1.1.5.dist-info/top_level.txt
polyp-1.1.5.dist-info/RECORD
