Metadata-Version: 2.1
Name: polyp
Version: 1.1.5
Summary: A renderer that creates gdsII files from an all-ascii human-readble layout language 
Author: zaphB
License-File: LICENSE.txt
Requires-Dist: numpy
Requires-Dist: gdspy
Requires-Dist: matplotlib
Requires-Dist: qrcode
